Metadata-Version: 2.1
Name: ws-cleanup-tool-test
Version: 23.6.1.4
Summary: Mend SCA Cleanup Tool
Home-page: https://github.com/whitesource-ps/mend-sca-cleanup-tool
Author: Mend Professional Services
Author-email: ps@whitesourcesoftware.com
License: LICENSE.txt
Platform: UNKNOWN
Classifier: Programming Language :: Python :: 3.7
Classifier: Programming Language :: Python :: 3.8
Classifier: Programming Language :: Python :: 3.9
Classifier: License :: OSI Approved :: Apache Software License
Classifier: Operating System :: OS Independent
Requires-Python: >=3.7
License-File: LICENSE
Requires-Dist: configparser (==5.3.0)
Requires-Dist: DateTime (~=4.3)
